stereosegger/__init__.py
stereosegger/cli/cli.py
stereosegger/cli/convert_saw_h5ad_to_segger_parquet.py
stereosegger/cli/create_dataset_fast.py
stereosegger/cli/predict.py
stereosegger/cli/predict_fast.py
stereosegger/cli/train_model.py
stereosegger/cli/utils.py
stereosegger/data/README.md
stereosegger/data/__init__.py
stereosegger/data/tx_graph.py
stereosegger/data/utils.py
stereosegger/data/parquet/__init__.py
stereosegger/data/parquet/_experimental.py
stereosegger/data/parquet/_ndtree.py
stereosegger/data/parquet/_utils.py
stereosegger/data/parquet/pyg_dataset.py
stereosegger/data/parquet/sample.py
stereosegger/data/parquet/transcript_embedding.py
stereosegger/models/README.md
stereosegger/models/__init__.py
stereosegger/models/segger_model.py
stereosegger/prediction/__init__.py
stereosegger/prediction/boundary.py
stereosegger/prediction/predict.py
stereosegger/prediction/predict_multigpu.py
stereosegger/prediction/predict_parquet.py
stereosegger/training/README.md
stereosegger/training/__init__.py
stereosegger/training/segger_data_module.py
stereosegger/training/train.py
stereosegger/validation/README.md
stereosegger/validation/__init__.py
stereosegger/validation/utils.py
stereosegger-0.2.3.dist-info/licenses/LICENSE
stereosegger-0.2.3.dist-info/METADATA
stereosegger-0.2.3.dist-info/WHEEL
stereosegger-0.2.3.dist-info/entry_points.txt
stereosegger-0.2.3.dist-info/top_level.txt
stereosegger-0.2.3.dist-info/RECORD
