Metadata-Version: 2.4
Name: stereosegger
Version: 0.2.3
Summary: Fast and accurate cell segmentation for single-molecule spatial omics (Stereo-seq)
Author-email: Elyas Heidari <elyas.heidari@dkfz-heidelberg.de>
License: MIT
Project-URL: bug_tracker, https://github.com/nrclaudio/stereosegger/issues
Project-URL: source_code, https://github.com/nrclaudio/stereosegger
Project-URL: repository, https://github.com/nrclaudio/stereosegger
Keywords: segmentation,deep learning,pytorch,geometric deep learning,stereo-seq
Classifier: Development Status :: 4 - Beta
Classifier: Intended Audience :: Science/Research
Classifier: License :: OSI Approved :: MIT License
Classifier: Programming Language :: Python :: 3
Classifier: Programming Language :: Python :: 3.10
Classifier: Topic :: Scientific/Engineering :: Bio-Informatics
Requires-Python: >=3.10
License-File: LICENSE
Requires-Dist: torch==2.5.1
Requires-Dist: torchvision==0.20.1
Requires-Dist: nvidia-nvjitlink-cu12>=12.4.127
Requires-Dist: distributed==2024.7.1
Requires-Dist: numpy>=1.24.4
Requires-Dist: pandas==2.1.4
Requires-Dist: scipy>=1.7.0
Requires-Dist: matplotlib>=3.4.0
Requires-Dist: seaborn>=0.11.0
Requires-Dist: tqdm>=4.61.0
Requires-Dist: lightning>=1.9.0
Requires-Dist: torchmetrics>=0.5.0
Requires-Dist: zarr<3.0.0,>=2.6.1
Requires-Dist: anndata==0.10.8
Requires-Dist: scanpy==1.10.2
Requires-Dist: squidpy==1.4.1
Requires-Dist: adjustText>=0.8
Requires-Dist: scikit-learn>=0.24.0
Requires-Dist: geopandas<1.0,>=0.9.0
Requires-Dist: shapely>=1.7.0
Requires-Dist: path>=17.0.0
Requires-Dist: pyarrow>=16.1.0
Requires-Dist: dask==2024.7.1
Requires-Dist: dask_geopandas>=0.4.0
Requires-Dist: dask-cuda>=23.10.0
Requires-Dist: torch-geometric>=2.3.0
Requires-Dist: pqdm>=0.2.0
Requires-Dist: rtree>=1.3.0
Requires-Dist: cudf-cu12<24.9.0,>=24.8.0
Requires-Dist: cuml-cu12<24.9.0,>=24.8.0
Requires-Dist: cugraph-cu12<24.9.0,>=24.8.0
Requires-Dist: cuspatial-cu12<24.9.0,>=24.8.0
Requires-Dist: cupy-cuda12x>=12.0.0
Provides-Extra: dev
Requires-Dist: pytest; extra == "dev"
Requires-Dist: black; extra == "dev"
Requires-Dist: flake8; extra == "dev"
Requires-Dist: twine>=4.0.2; extra == "dev"
Provides-Extra: tests
Requires-Dist: pytest; extra == "tests"
Requires-Dist: coverage; extra == "tests"
Dynamic: license-file
